wasiliana/__init__.py
pytek_wasiliana-1.2.dist-info/LICENCE
pytek_wasiliana-1.2.dist-info/METADATA
pytek_wasiliana-1.2.dist-info/WHEEL
pytek_wasiliana-1.2.dist-info/entry_points.txt
pytek_wasiliana-1.2.dist-info/top_level.txt
pytek_wasiliana-1.2.dist-info/RECORD
